odoa.py
python_quran_odoa-2.0.0.dist-info/LICENSE
python_quran_odoa-2.0.0.dist-info/METADATA
python_quran_odoa-2.0.0.dist-info/WHEEL
python_quran_odoa-2.0.0.dist-info/top_level.txt
python_quran_odoa-2.0.0.dist-info/RECORD
